pykitinfo/__init__.py
pykitinfo/detect_edbg_tools.py
pykitinfo/detect_legacy_pickit3_tools.py
pykitinfo/detect_mcp2221a_tools.py
pykitinfo/detect_microchip_tools.py
pykitinfo/genx.py
pykitinfo/logging.yaml
pykitinfo/pykitinfo.py
pykitinfo/pykitinfo_cli.py
pykitinfo/tools.py
pykitinfo-1.4.1.26.dist-info/licenses/LICENSE.txt
pykitinfo-1.4.1.26.dist-info/METADATA
pykitinfo-1.4.1.26.dist-info/WHEEL
pykitinfo-1.4.1.26.dist-info/entry_points.txt
pykitinfo-1.4.1.26.dist-info/top_level.txt
pykitinfo-1.4.1.26.dist-info/RECORD
