Metadata-Version: 2.4
Name: pykitinfo
Version: 1.4.1.26
Summary: A provider of information about connected Microchip development kits
Author-email: Microchip Technology <support@microchip.com>
License: MIT
Project-URL: Homepage, https://github.com/microchip-pic-avr-tools/pykitinfo
Keywords: Microchip,Xplained Pro,EDBG,nEDBG,Curiosity Nano,PKOB nano,debugger,MCP2221A,PkOB4,PICkit4,PICkit5,Snap,PICkit Basic,Curiosity Ultra,Curiosity Pro
Classifier: Development Status :: 5 - Production/Stable
Classifier: Intended Audience :: Developers
Classifier: Topic :: Software Development :: Embedded Systems
Classifier: Programming Language :: Python :: 3
Classifier: Programming Language :: Python :: 3.9
Classifier: Programming Language :: Python :: 3.10
Classifier: Programming Language :: Python :: 3.11
Classifier: Programming Language :: Python :: 3.12
Classifier: Programming Language :: Python :: 3.13
Classifier: Operating System :: Microsoft :: Windows
Classifier: Operating System :: POSIX :: Linux
Classifier: Operating System :: MacOS
Classifier: License :: OSI Approved :: MIT License
Requires-Python: >=3.8
License-File: LICENSE.txt
Requires-Dist: pyusb>=1.2.0
Requires-Dist: PyYAML
Requires-Dist: appdirs
Requires-Dist: libusb_package
Requires-Dist: pyedbglib~=2.22
Requires-Dist: pydebuggerconfig>=3.5
Provides-Extra: dev
Requires-Dist: pylint>=2.15; extra == "dev"
Provides-Extra: test
Requires-Dist: mock; extra == "test"
Requires-Dist: pytest; extra == "test"
Provides-Extra: doc
Requires-Dist: mock; extra == "doc"
Requires-Dist: sphinx; extra == "doc"
Dynamic: license-file
